{
  "kind": "youtube#searchListResponse",
  "etag": "IOXykzcI-Zwr3hfQXz_h6YScP3c",
  "nextPageToken": "CAMQAA",
  "regionCode": "VN",
  "pageInfo": {
    "totalResults": 1000000,
    "resultsPerPage": 3
  },
  "items": [
    {
      "kind": "youtube#searchResult",
      "etag": "xSI7efFZLLDnRiRLl8LoLHSXUFU",
      "id": {
        "kind": "youtube#video",
        "videoId": "ARt9HV9T0w8"
      },
      "snippet": {
        "publishedAt": "2016-06-22T19:29:48Z",
        "channelId": "UC0RKPIqgL98gqKmYlr-V5-A",
        "title": "Gloria Gaynor - I Will Survive [Official Video] 1978 [Audio iTunes Plus AAC M4A]",
        "description": "«I Will Survive» —en español: «Sobreviviré»— es una canción disco originalmente interpretada por la cantante estadounidense Gloria Gaynor, lanzada en ...",
        "thumbnails": {
          "default": {
            "url": "https://i.ytimg.com/vi/ARt9HV9T0w8/default.jpg",
            "width": 120,
            "height": 90
          },
          "medium": {
            "url": "https://i.ytimg.com/vi/ARt9HV9T0w8/mqdefault.jpg",
            "width": 320,
            "height": 180
          },
          "high": {
            "url": "https://i.ytimg.com/vi/ARt9HV9T0w8/hqdefault.jpg",
            "width": 480,
            "height": 360
          }
        },
        "channelTitle": "Solrac Etnevic",
        "liveBroadcastContent": "none",
        "publishTime": "2016-06-22T19:29:48Z"
      }
    },
    {
      "kind": "youtube#searchResult",
      "etag": "N6PXBeyA8xtYIMffA3GNhlntBTM",
      "id": {
        "kind": "youtube#video",
        "videoId": "sZ-SwJjkSyw"
      },
      "snippet": {
        "publishedAt": "2016-08-31T15:22:36Z",
        "channelId": "UCSIIxy9Lps3WYucDy7N55PQ",
        "title": "Gloria Gaynor - I Will Survive (Lyrics)",
        "description": "If you have any requests let me know in the comment section below.",
        "thumbnails": {
          "default": {
            "url": "https://i.ytimg.com/vi/sZ-SwJjkSyw/default.jpg",
            "width": 120,
            "height": 90
          },
          "medium": {
            "url": "https://i.ytimg.com/vi/sZ-SwJjkSyw/mqdefault.jpg",
            "width": 320,
            "height": 180
          },
          "high": {
            "url": "https://i.ytimg.com/vi/sZ-SwJjkSyw/hqdefault.jpg",
            "width": 480,
            "height": 360
          }
        },
        "channelTitle": "Jessica Clarke",
        "liveBroadcastContent": "none",
        "publishTime": "2016-08-31T15:22:36Z"
      }
    },
    {
      "kind": "youtube#searchResult",
      "etag": "-jVvQ_t7hq-zRnm7GSbhBtb18H4",
      "id": {
        "kind": "youtube#video",
        "videoId": "_OaEnA4diCI"
      },
      "snippet": {
        "publishedAt": "2013-02-10T03:23:44Z",
        "channelId": "UC3CIs3C7V5PTBAA-hFc-96w",
        "title": "I Will Survive - Gloria Gaynor &quot;Live&quot;",
        "description": "PBS televised performance with Greg Phillinganes (keyboards) John Robinson (drums) Michael Angel Alvarado (guitar) Ian Martin (bass) Noriko (synth) ...",
        "thumbnails": {
          "default": {
            "url": "https://i.ytimg.com/vi/_OaEnA4diCI/default.jpg",
            "width": 120,
            "height": 90
          },
          "medium": {
            "url": "https://i.ytimg.com/vi/_OaEnA4diCI/mqdefault.jpg",
            "width": 320,
            "height": 180
          },
          "high": {
            "url": "https://i.ytimg.com/vi/_OaEnA4diCI/hqdefault.jpg",
            "width": 480,
            "height": 360
          }
        },
        "channelTitle": "Michael Angel",
        "liveBroadcastContent": "none",
        "publishTime": "2013-02-10T03:23:44Z"
      }
    }
  ]
}
