{
  "kind": "youtube#searchListResponse",
  "etag": "NUgk_Y-SdNoI9px_3s1iquZKUZQ",
  "nextPageToken": "CAMQAA",
  "regionCode": "VN",
  "pageInfo": {
    "totalResults": 706138,
    "resultsPerPage": 3
  },
  "items": [
    {
      "kind": "youtube#searchResult",
      "etag": "GR2JwoGZpnFvduTiayQn8JMKqSE",
      "id": {
        "kind": "youtube#video",
        "videoId": "i3Jv9fNPjgk"
      },
      "snippet": {
        "publishedAt": "2011-09-13T06:18:39Z",
        "channelId": "UCD4UMQ7oryQQq5gqZStJQ6g",
        "title": "AZEALIA BANKS - 212 FT. LAZY JAY",
        "description": "Azealia Banks - \"212\" Video (2011) www.azealiabanks.com.",
        "thumbnails": {
          "default": {
            "url": "https://i.ytimg.com/vi/i3Jv9fNPjgk/default.jpg",
            "width": 120,
            "height": 90
          },
          "medium": {
            "url": "https://i.ytimg.com/vi/i3Jv9fNPjgk/mqdefault.jpg",
            "width": 320,
            "height": 180
          },
          "high": {
            "url": "https://i.ytimg.com/vi/i3Jv9fNPjgk/hqdefault.jpg",
            "width": 480,
            "height": 360
          }
        },
        "channelTitle": "Azealia Banks",
        "liveBroadcastContent": "none",
        "publishTime": "2011-09-13T06:18:39Z"
      }
    },
    {
      "kind": "youtube#searchResult",
      "etag": "McTE4CwdzRs-mm8HlKNkYqfFnVE",
      "id": {
        "kind": "youtube#video",
        "videoId": "bC6gTNKl-ak"
      },
      "snippet": {
        "publishedAt": "2018-09-25T19:00:02Z",
        "channelId": "UCPR8RgeVZjJ3ogh45KyepCg",
        "title": "Azealia Banks - 212 (Official Audio) ft. Lazy Jay",
        "description": "Azealia Banks - 212 (Official Audio) ft Lazy Jay Copyright (C) 2018 Prospect Park --- Powered by http://www.vydia.com http://vevo.ly/dp9qQJ.",
        "thumbnails": {
          "default": {
            "url": "https://i.ytimg.com/vi/bC6gTNKl-ak/default.jpg",
            "width": 120,
            "height": 90
          },
          "medium": {
            "url": "https://i.ytimg.com/vi/bC6gTNKl-ak/mqdefault.jpg",
            "width": 320,
            "height": 180
          },
          "high": {
            "url": "https://i.ytimg.com/vi/bC6gTNKl-ak/hqdefault.jpg",
            "width": 480,
            "height": 360
          }
        },
        "channelTitle": "AzealiaBanksVEVO",
        "liveBroadcastContent": "none",
        "publishTime": "2018-09-25T19:00:02Z"
      }
    },
    {
      "kind": "youtube#searchResult",
      "etag": "343qYJD0LjhjnYmyV17hJLKDcdk",
      "id": {
        "kind": "youtube#video",
        "videoId": "UDIealZCXDw"
      },
      "snippet": {
        "publishedAt": "2011-11-24T19:16:13Z",
        "channelId": "UC9kc8RbYnGxt01-hTqS57NQ",
        "title": "Azealia Banks - 212 Lyrics",
        "description": "212 by Azealia Banks.",
        "thumbnails": {
          "default": {
            "url": "https://i.ytimg.com/vi/UDIealZCXDw/default.jpg",
            "width": 120,
            "height": 90
          },
          "medium": {
            "url": "https://i.ytimg.com/vi/UDIealZCXDw/mqdefault.jpg",
            "width": 320,
            "height": 180
          },
          "high": {
            "url": "https://i.ytimg.com/vi/UDIealZCXDw/hqdefault.jpg",
            "width": 480,
            "height": 360
          }
        },
        "channelTitle": "amamoslavida",
        "liveBroadcastContent": "none",
        "publishTime": "2011-11-24T19:16:13Z"
      }
    }
  ]
}
