{
  "kind": "youtube#searchListResponse",
  "etag": "gEIlkS1QdH0JF30p-6jhF9LllJc",
  "nextPageToken": "CAMQAA",
  "regionCode": "VN",
  "pageInfo": {
    "totalResults": 1000000,
    "resultsPerPage": 3
  },
  "items": [
    {
      "kind": "youtube#searchResult",
      "etag": "iQpLxmooUJbYtS5PEoT9x0lU9hA",
      "id": {
        "kind": "youtube#video",
        "videoId": "-nwdjQmc_N8"
      },
      "snippet": {
        "publishedAt": "2012-01-18T08:00:00Z",
        "channelId": "UCcemkeZKHXdDkIinIwar1pg",
        "title": "Emeli Sandé - Next To Me (Official Music Video)",
        "description": "UK: Buy 'Next To Me' on iTunes here: http://smarturl.it/EmeliNextToMe From the UK's biggest selling debut album of 2012 'Our Version Of Events': ...",
        "thumbnails": {
          "default": {
            "url": "https://i.ytimg.com/vi/-nwdjQmc_N8/default.jpg",
            "width": 120,
            "height": 90
          },
          "medium": {
            "url": "https://i.ytimg.com/vi/-nwdjQmc_N8/mqdefault.jpg",
            "width": 320,
            "height": 180
          },
          "high": {
            "url": "https://i.ytimg.com/vi/-nwdjQmc_N8/hqdefault.jpg",
            "width": 480,
            "height": 360
          }
        },
        "channelTitle": "EmeliSandeVEVO",
        "liveBroadcastContent": "none",
        "publishTime": "2012-01-18T08:00:00Z"
      }
    },
    {
      "kind": "youtube#searchResult",
      "etag": "raQe6me-zVtprOVPcZ20LdJIapY",
      "id": {
        "kind": "youtube#video",
        "videoId": "co1AT-Rr0cc"
      },
      "snippet": {
        "publishedAt": "2012-01-06T13:09:07Z",
        "channelId": "UC9J4cBgrKRQG_1Qv99dSbSg",
        "title": "Emeli Sandé - Next To Me (Lyric Video)",
        "description": "Emeli Sandé - Next To Me (Lyric Video) Out now on the Special Edition of 'Our Version Of Events': http://hyperurl.co/OurVersionSpecial Lyrics: You won't find ...",
        "thumbnails": {
          "default": {
            "url": "https://i.ytimg.com/vi/co1AT-Rr0cc/default.jpg",
            "width": 120,
            "height": 90
          },
          "medium": {
            "url": "https://i.ytimg.com/vi/co1AT-Rr0cc/mqdefault.jpg",
            "width": 320,
            "height": 180
          },
          "high": {
            "url": "https://i.ytimg.com/vi/co1AT-Rr0cc/hqdefault.jpg",
            "width": 480,
            "height": 360
          }
        },
        "channelTitle": "Emeli Sandé",
        "liveBroadcastContent": "none",
        "publishTime": "2012-01-06T13:09:07Z"
      }
    },
    {
      "kind": "youtube#searchResult",
      "etag": "zDfSVwXuq6wOkvB5DMdbYJ6fD7I",
      "id": {
        "kind": "youtube#video",
        "videoId": "N7wIvh1LjOk"
      },
      "snippet": {
        "publishedAt": "2013-01-31T00:00:26Z",
        "channelId": "UCcemkeZKHXdDkIinIwar1pg",
        "title": "Emeli Sandé - Next to Me (Live At the Royal Albert Hall)",
        "description": "DVD available 18th February -- Pre-order here:http://smarturl.it/emelialberthall Introducing a collectable Live CD/DVD release to commemorate Emeli's first ever ...",
        "thumbnails": {
          "default": {
            "url": "https://i.ytimg.com/vi/N7wIvh1LjOk/default.jpg",
            "width": 120,
            "height": 90
          },
          "medium": {
            "url": "https://i.ytimg.com/vi/N7wIvh1LjOk/mqdefault.jpg",
            "width": 320,
            "height": 180
          },
          "high": {
            "url": "https://i.ytimg.com/vi/N7wIvh1LjOk/hqdefault.jpg",
            "width": 480,
            "height": 360
          }
        },
        "channelTitle": "EmeliSandeVEVO",
        "liveBroadcastContent": "none",
        "publishTime": "2013-01-31T00:00:26Z"
      }
    }
  ]
}
