{
  "kind": "youtube#searchListResponse",
  "etag": "-hzB1znRI2_zT-GSzHAtewL3iRI",
  "nextPageToken": "CAMQAA",
  "regionCode": "VN",
  "pageInfo": {
    "totalResults": 107910,
    "resultsPerPage": 3
  },
  "items": [
    {
      "kind": "youtube#searchResult",
      "etag": "L8-TZP79KvbfBwtrHo4loYb2qIQ",
      "id": {
        "kind": "youtube#video",
        "videoId": "1jOk8dk-qaU"
      },
      "snippet": {
        "publishedAt": "2007-05-25T20:41:21Z",
        "channelId": "UCDE5Ezmxq1bNVak4lmkpCMw",
        "title": "The Offspring - &quot;Come Out And Play&quot;",
        "description": "Listen to the full album at http://bit.ly/12Okmvb \"Come Out And Play\" by The Offspring from the album 'Smash' Get 'Smash' on iTunes: http://bit.ly/1dXZHdk ...",
        "thumbnails": {
          "default": {
            "url": "https://i.ytimg.com/vi/1jOk8dk-qaU/default.jpg",
            "width": 120,
            "height": 90
          },
          "medium": {
            "url": "https://i.ytimg.com/vi/1jOk8dk-qaU/mqdefault.jpg",
            "width": 320,
            "height": 180
          },
          "high": {
            "url": "https://i.ytimg.com/vi/1jOk8dk-qaU/hqdefault.jpg",
            "width": 480,
            "height": 360
          }
        },
        "channelTitle": "Epitaph Records",
        "liveBroadcastContent": "none",
        "publishTime": "2007-05-25T20:41:21Z"
      }
    },
    {
      "kind": "youtube#searchResult",
      "etag": "6O72ZLIulnyhEk-zMrM5V11fkDM",
      "id": {
        "kind": "youtube#video",
        "videoId": "8FWdQVNeTlI"
      },
      "snippet": {
        "publishedAt": "2011-01-27T20:12:29Z",
        "channelId": "UCVFFqPRDMohT9TComUizg0Q",
        "title": "Keep &#39;Em Separated - The Offspring(LYRICS)",
        "description": "",
        "thumbnails": {
          "default": {
            "url": "https://i.ytimg.com/vi/8FWdQVNeTlI/default.jpg",
            "width": 120,
            "height": 90
          },
          "medium": {
            "url": "https://i.ytimg.com/vi/8FWdQVNeTlI/mqdefault.jpg",
            "width": 320,
            "height": 180
          },
          "high": {
            "url": "https://i.ytimg.com/vi/8FWdQVNeTlI/hqdefault.jpg",
            "width": 480,
            "height": 360
          }
        },
        "channelTitle": "Lina Sjökvist",
        "liveBroadcastContent": "none",
        "publishTime": "2011-01-27T20:12:29Z"
      }
    },
    {
      "kind": "youtube#searchResult",
      "etag": "86UbQG_A7G-p_2iDaywhJeAl9uA",
      "id": {
        "kind": "youtube#video",
        "videoId": "2MQIwIxvJIY"
      },
      "snippet": {
        "publishedAt": "2021-06-17T22:28:33Z",
        "channelId": "UCkZqulV4hovQ88Oi0htrjFA",
        "title": "The Offspring - Come Out And Play - 7/23/1999 - Woodstock 99 East Stage",
        "description": "Recorded 7/23/1999 - Woodstock 99 East Stage (Rome, NY) Visit Wolfgang's https://www.wolfgangs.com/music/ to stream concerts from thousands of legendary ...",
        "thumbnails": {
          "default": {
            "url": "https://i.ytimg.com/vi/2MQIwIxvJIY/default.jpg",
            "width": 120,
            "height": 90
          },
          "medium": {
            "url": "https://i.ytimg.com/vi/2MQIwIxvJIY/mqdefault.jpg",
            "width": 320,
            "height": 180
          },
          "high": {
            "url": "https://i.ytimg.com/vi/2MQIwIxvJIY/hqdefault.jpg",
            "width": 480,
            "height": 360
          }
        },
        "channelTitle": "Alt Rock on MV",
        "liveBroadcastContent": "none",
        "publishTime": "2021-06-17T22:28:33Z"
      }
    }
  ]
}
