{
  "kind": "youtube#searchListResponse",
  "etag": "KgUHULM7nnfUTOu1MUdepYn22MM",
  "nextPageToken": "CAMQAA",
  "regionCode": "VN",
  "pageInfo": {
    "totalResults": 129395,
    "resultsPerPage": 3
  },
  "items": [
    {
      "kind": "youtube#searchResult",
      "etag": "n9Z8wlEfxqoPujJMACy9Fi8jN40",
      "id": {
        "kind": "youtube#video",
        "videoId": "k-9DOwrLdkg"
      },
      "snippet": {
        "publishedAt": "2019-08-05T03:06:12Z",
        "channelId": "UCTU5PYs3vQvY8b9kOMoQGUg",
        "title": "euphoria | official song by labrinth &amp; zendaya - “all for us” full song (s1 ep8) | HBO",
        "description": "till then. stream all for us by labrinth & zendaya: https://euphoria.lnk.to/AllForUs #EUPHORIA #zendaya #labrinth Subscribe to euphoria on YouTube: ...",
        "thumbnails": {
          "default": {
            "url": "https://i.ytimg.com/vi/k-9DOwrLdkg/default.jpg",
            "width": 120,
            "height": 90
          },
          "medium": {
            "url": "https://i.ytimg.com/vi/k-9DOwrLdkg/mqdefault.jpg",
            "width": 320,
            "height": 180
          },
          "high": {
            "url": "https://i.ytimg.com/vi/k-9DOwrLdkg/hqdefault.jpg",
            "width": 480,
            "height": 360
          }
        },
        "channelTitle": "euphoria",
        "liveBroadcastContent": "none",
        "publishTime": "2019-08-05T03:06:12Z"
      }
    },
    {
      "kind": "youtube#searchResult",
      "etag": "XpJxnO3Y30NaIgOZf8xaedEOT7w",
      "id": {
        "kind": "youtube#video",
        "videoId": "trXGmmWFxQo"
      },
      "snippet": {
        "publishedAt": "2019-08-06T19:00:06Z",
        "channelId": "UCy6uEbrpWVmbh0oxzhSaB9Q",
        "title": "All For Us - Zendaya Only (Euphoria HBO Original Soundtrack)",
        "description": "All For Us by Labrinth and Zendaya is a masterpiece, and I wanted to make a \"Zendaya only\" version so that's what I did. Hope I won't get sued for this.",
        "thumbnails": {
          "default": {
            "url": "https://i.ytimg.com/vi/trXGmmWFxQo/default.jpg",
            "width": 120,
            "height": 90
          },
          "medium": {
            "url": "https://i.ytimg.com/vi/trXGmmWFxQo/mqdefault.jpg",
            "width": 320,
            "height": 180
          },
          "high": {
            "url": "https://i.ytimg.com/vi/trXGmmWFxQo/hqdefault.jpg",
            "width": 480,
            "height": 360
          }
        },
        "channelTitle": "dérive.",
        "liveBroadcastContent": "none",
        "publishTime": "2019-08-06T19:00:06Z"
      }
    },
    {
      "kind": "youtube#searchResult",
      "etag": "cL1xJr66CdE4rVmrTSQmfRGRoYg",
      "id": {
        "kind": "youtube#video",
        "videoId": "4MCJ3lgFqbg"
      },
      "snippet": {
        "publishedAt": "2019-08-09T11:00:02Z",
        "channelId": "UCxaRKrg-61IZ24sFZRQ3b_w",
        "title": "Labrinth, Zendaya - All For Us (Lyrics)",
        "description": "Labrinth, Zendaya - All For Us (Lyrics) ↪︎ Stream/Download: https://direct-link.net/36056/AllForUs Music submissions: https://royalvibes.edmdistrict.com/ Email ...",
        "thumbnails": {
          "default": {
            "url": "https://i.ytimg.com/vi/4MCJ3lgFqbg/default.jpg",
            "width": 120,
            "height": 90
          },
          "medium": {
            "url": "https://i.ytimg.com/vi/4MCJ3lgFqbg/mqdefault.jpg",
            "width": 320,
            "height": 180
          },
          "high": {
            "url": "https://i.ytimg.com/vi/4MCJ3lgFqbg/hqdefault.jpg",
            "width": 480,
            "height": 360
          }
        },
        "channelTitle": "Royal Vibes",
        "liveBroadcastContent": "none",
        "publishTime": "2019-08-09T11:00:02Z"
      }
    }
  ]
}
