{
  "kind": "youtube#searchListResponse",
  "etag": "vppp8Tl6Qd2ajhndkrxd343VbGk",
  "nextPageToken": "CAMQAA",
  "regionCode": "VN",
  "pageInfo": {
    "totalResults": 1000000,
    "resultsPerPage": 3
  },
  "items": [
    {
      "kind": "youtube#searchResult",
      "etag": "lval6JnznLpSRQ2JRwAR5Y5h08Y",
      "id": {
        "kind": "youtube#video",
        "videoId": "nYh-n7EOtMA"
      },
      "snippet": {
        "publishedAt": "2016-02-11T04:00:01Z",
        "channelId": "UCmKdSrwf1e8coqAzUsrVHZw",
        "title": "Sia - Cheap Thrills (Lyric Video) ft. Sean Paul",
        "description": "Official Lyric Video for \"Cheap Thrills\" by Sia feat. Sean Paul Listen to Sia: https://sia.lnk.to/listenYD Watch more Sia videos: https://sia.lnk.to/listenYD/youtube ...",
        "thumbnails": {
          "default": {
            "url": "https://i.ytimg.com/vi/nYh-n7EOtMA/default.jpg",
            "width": 120,
            "height": 90
          },
          "medium": {
            "url": "https://i.ytimg.com/vi/nYh-n7EOtMA/mqdefault.jpg",
            "width": 320,
            "height": 180
          },
          "high": {
            "url": "https://i.ytimg.com/vi/nYh-n7EOtMA/hqdefault.jpg",
            "width": 480,
            "height": 360
          }
        },
        "channelTitle": "SiaVEVO",
        "liveBroadcastContent": "none",
        "publishTime": "2016-02-11T04:00:01Z"
      }
    },
    {
      "kind": "youtube#searchResult",
      "etag": "E84edWMQnqjhAOK5ddns4pttNrY",
      "id": {
        "kind": "youtube#video",
        "videoId": "PonUS87Yeqw"
      },
      "snippet": {
        "publishedAt": "2020-05-11T16:47:17Z",
        "channelId": "UC4JUzmhmiGmPl7uzLpzODyw",
        "title": "Sia - Cheap Thrills (Lyrics) ft. Sean Paul",
        "description": "Sia - Cheap Thrills (Lyrics) ft. Sean Paul Stream/Download: https://lnk.to/CheapThrillsSia Follow our Spotify Playlist: https://loku.lnk.to/Spotify Sia ...",
        "thumbnails": {
          "default": {
            "url": "https://i.ytimg.com/vi/PonUS87Yeqw/default.jpg",
            "width": 120,
            "height": 90
          },
          "medium": {
            "url": "https://i.ytimg.com/vi/PonUS87Yeqw/mqdefault.jpg",
            "width": 320,
            "height": 180
          },
          "high": {
            "url": "https://i.ytimg.com/vi/PonUS87Yeqw/hqdefault.jpg",
            "width": 480,
            "height": 360
          }
        },
        "channelTitle": "Loku",
        "liveBroadcastContent": "none",
        "publishTime": "2020-05-11T16:47:17Z"
      }
    },
    {
      "kind": "youtube#searchResult",
      "etag": "3YvlbyF0MmgqH6rL6-W_chC7K4o",
      "id": {
        "kind": "youtube#video",
        "videoId": "8KpazOk5IGU"
      },
      "snippet": {
        "publishedAt": "2017-06-10T20:42:33Z",
        "channelId": "UCZzwjZPc6R_PbnDgFVMwlvQ",
        "title": "Sean Paul - &#39;Cheap Thrills&#39;  (Live At Capital’s Summertime Ball 2017)",
        "description": "Subscribe: http://bit.ly/SubscribeToCapitalFM Get involved with the UK's No. 1 Hit Music Station! Website: http://www.capitalfm.com/ Facebook: ...",
        "thumbnails": {
          "default": {
            "url": "https://i.ytimg.com/vi/8KpazOk5IGU/default.jpg",
            "width": 120,
            "height": 90
          },
          "medium": {
            "url": "https://i.ytimg.com/vi/8KpazOk5IGU/mqdefault.jpg",
            "width": 320,
            "height": 180
          },
          "high": {
            "url": "https://i.ytimg.com/vi/8KpazOk5IGU/hqdefault.jpg",
            "width": 480,
            "height": 360
          }
        },
        "channelTitle": "Capital FM",
        "liveBroadcastContent": "none",
        "publishTime": "2017-06-10T20:42:33Z"
      }
    }
  ]
}
