{
  "kind": "youtube#searchListResponse",
  "etag": "kgMAKDtkE_N6hA165X6bgMpIpnw",
  "nextPageToken": "CAMQAA",
  "regionCode": "VN",
  "pageInfo": {
    "totalResults": 1000000,
    "resultsPerPage": 3
  },
  "items": [
    {
      "kind": "youtube#searchResult",
      "etag": "FCiHv5Nbb-xyZOQE8EUwfdGCSJU",
      "id": {
        "kind": "youtube#video",
        "videoId": "pBI3lc18k8Q"
      },
      "snippet": {
        "publishedAt": "2009-10-16T05:21:19Z",
        "channelId": "UCe3yZzUwpmy2eKKmF9svX0Q",
        "title": "Jason Derulo - Whatcha Say [Official Music Video]",
        "description": "Watch the official music video for Whatcha Say by Jason Derulo from the album Jason Derülo. Subscribe to the channel: ...",
        "thumbnails": {
          "default": {
            "url": "https://i.ytimg.com/vi/pBI3lc18k8Q/default.jpg",
            "width": 120,
            "height": 90
          },
          "medium": {
            "url": "https://i.ytimg.com/vi/pBI3lc18k8Q/mqdefault.jpg",
            "width": 320,
            "height": 180
          },
          "high": {
            "url": "https://i.ytimg.com/vi/pBI3lc18k8Q/hqdefault.jpg",
            "width": 480,
            "height": 360
          }
        },
        "channelTitle": "Jason Derulo",
        "liveBroadcastContent": "none",
        "publishTime": "2009-10-16T05:21:19Z"
      }
    },
    {
      "kind": "youtube#searchResult",
      "etag": "wYATF1YRTHhSrXQJemNUlm7ee2g",
      "id": {
        "kind": "youtube#video",
        "videoId": "tnOXjYootTM"
      },
      "snippet": {
        "publishedAt": "2019-04-14T12:33:32Z",
        "channelId": "UCNqFDjYTexJDET3rPDrmJKg",
        "title": "Jason Derulo - Whatcha Say (Lyrics)",
        "description": "Jason Derulo - Whatcha Say (Lyrics) ⏬ Download / Stream: http://www.smarturl.it/EverythingIs4 Turn on notifications to stay updated with new uploads!",
        "thumbnails": {
          "default": {
            "url": "https://i.ytimg.com/vi/tnOXjYootTM/default.jpg",
            "width": 120,
            "height": 90
          },
          "medium": {
            "url": "https://i.ytimg.com/vi/tnOXjYootTM/mqdefault.jpg",
            "width": 320,
            "height": 180
          },
          "high": {
            "url": "https://i.ytimg.com/vi/tnOXjYootTM/hqdefault.jpg",
            "width": 480,
            "height": 360
          }
        },
        "channelTitle": "7clouds",
        "liveBroadcastContent": "none",
        "publishTime": "2019-04-14T12:33:32Z"
      }
    },
    {
      "kind": "youtube#searchResult",
      "etag": "3CANm4BH6a00bghcDX2YfIA9GD0",
      "id": {
        "kind": "youtube#video",
        "videoId": "kxLiDtaL4HM"
      },
      "snippet": {
        "publishedAt": "2009-12-04T21:56:00Z",
        "channelId": "UCe3yZzUwpmy2eKKmF9svX0Q",
        "title": "Jason Derulo - Whatcha Say [Acoustic Version] (Video)",
        "description": "Jason Derulo's brand new album “Everything Is 4” is available now on iTunes! Download it here: http://www.smarturl.it/EverythingIs4 The new album features ...",
        "thumbnails": {
          "default": {
            "url": "https://i.ytimg.com/vi/kxLiDtaL4HM/default.jpg",
            "width": 120,
            "height": 90
          },
          "medium": {
            "url": "https://i.ytimg.com/vi/kxLiDtaL4HM/mqdefault.jpg",
            "width": 320,
            "height": 180
          },
          "high": {
            "url": "https://i.ytimg.com/vi/kxLiDtaL4HM/hqdefault.jpg",
            "width": 480,
            "height": 360
          }
        },
        "channelTitle": "Jason Derulo",
        "liveBroadcastContent": "none",
        "publishTime": "2009-12-04T21:56:00Z"
      }
    }
  ]
}
