{
  "kind": "youtube#searchListResponse",
  "etag": "9svV7KPA0Vl-RZgzqsWbEje0Lzw",
  "nextPageToken": "CAMQAA",
  "regionCode": "VN",
  "pageInfo": {
    "totalResults": 1000000,
    "resultsPerPage": 3
  },
  "items": [
    {
      "kind": "youtube#searchResult",
      "etag": "JqTS8jl7g5e4u9x8apr6-oVQcFw",
      "id": {
        "kind": "youtube#video",
        "videoId": "EVBsypHzF3U"
      },
      "snippet": {
        "publishedAt": "2010-03-16T01:08:05Z",
        "channelId": "UC07Kxew-cMIaykMOkzqHtBQ",
        "title": "Lady Gaga - Telephone ft. Beyoncé (Official Music Video)",
        "description": "CHROMATICA” THE SIXTH ALBUM BY LADY GAGA OUT NOW http://smarturl.it/Chromatica “RAIN ON ME” THE NEW SINGLE & VIDEO FROM LADY GAGA ...",
        "thumbnails": {
          "default": {
            "url": "https://i.ytimg.com/vi/EVBsypHzF3U/default.jpg",
            "width": 120,
            "height": 90
          },
          "medium": {
            "url": "https://i.ytimg.com/vi/EVBsypHzF3U/mqdefault.jpg",
            "width": 320,
            "height": 180
          },
          "high": {
            "url": "https://i.ytimg.com/vi/EVBsypHzF3U/hqdefault.jpg",
            "width": 480,
            "height": 360
          }
        },
        "channelTitle": "LadyGagaVEVO",
        "liveBroadcastContent": "none",
        "publishTime": "2010-03-16T01:08:05Z"
      }
    },
    {
      "kind": "youtube#searchResult",
      "etag": "pQkDc56PgXBKs1xu2jR4clrRj5s",
      "id": {
        "kind": "youtube#video",
        "videoId": "pNcvmwxoK2g"
      },
      "snippet": {
        "publishedAt": "2013-12-16T00:28:18Z",
        "channelId": "UCg2WGcVOFhTbbiYiZcVVcNw",
        "title": "Lady Gaga - Telephone (Audio) ft. Beyoncé",
        "description": "",
        "thumbnails": {
          "default": {
            "url": "https://i.ytimg.com/vi/pNcvmwxoK2g/default.jpg",
            "width": 120,
            "height": 90
          },
          "medium": {
            "url": "https://i.ytimg.com/vi/pNcvmwxoK2g/mqdefault.jpg",
            "width": 320,
            "height": 180
          },
          "high": {
            "url": "https://i.ytimg.com/vi/pNcvmwxoK2g/hqdefault.jpg",
            "width": 480,
            "height": 360
          }
        },
        "channelTitle": "Joe Coleman",
        "liveBroadcastContent": "none",
        "publishTime": "2013-12-16T00:28:18Z"
      }
    },
    {
      "kind": "youtube#searchResult",
      "etag": "OFS_3RBkd_VHYoUBoBS-p8zKoIE",
      "id": {
        "kind": "youtube#video",
        "videoId": "Uv9BsncPCqQ"
      },
      "snippet": {
        "publishedAt": "2020-04-30T07:16:39Z",
        "channelId": "UCkSYzQ9txOvcLVCayei0Y8A",
        "title": "Lady Gaga - Telephone ft. Beyoncé(Lyrics)",
        "description": "Lady Gaga - Telephone ft. Beyoncé(Lyrics) Lady Gaga\" Facebook: http://gaga.lk/facebook Twitter: http://gaga.lk/Twitter Instagram: http://gaga.lk/Instagram ...",
        "thumbnails": {
          "default": {
            "url": "https://i.ytimg.com/vi/Uv9BsncPCqQ/default.jpg",
            "width": 120,
            "height": 90
          },
          "medium": {
            "url": "https://i.ytimg.com/vi/Uv9BsncPCqQ/mqdefault.jpg",
            "width": 320,
            "height": 180
          },
          "high": {
            "url": "https://i.ytimg.com/vi/Uv9BsncPCqQ/hqdefault.jpg",
            "width": 480,
            "height": 360
          }
        },
        "channelTitle": "LyricLover",
        "liveBroadcastContent": "none",
        "publishTime": "2020-04-30T07:16:39Z"
      }
    }
  ]
}
