{
  "kind": "youtube#searchListResponse",
  "etag": "jvOqMaMXQ-xv2oq9uLR3QCzI5ys",
  "nextPageToken": "CAMQAA",
  "regionCode": "VN",
  "pageInfo": {
    "totalResults": 1000000,
    "resultsPerPage": 3
  },
  "items": [
    {
      "kind": "youtube#searchResult",
      "etag": "lyBuCuqZ6G3ZN6xKPc-zT-l56bU",
      "id": {
        "kind": "youtube#video",
        "videoId": "V0lw3qylVfY"
      },
      "snippet": {
        "publishedAt": "2015-10-02T14:30:00Z",
        "channelId": "UCzzXsnHsEmGorQ6xAKL2sZA",
        "title": "X Ambassadors - Unsteady",
        "description": "The ORION Tour is coming to your city: https://www.xambassadors.com/tour Get X Ambassadors' VHS, out now: http://smarturl.it/VHS Get the Unsteady T-Shirt ...",
        "thumbnails": {
          "default": {
            "url": "https://i.ytimg.com/vi/V0lw3qylVfY/default.jpg",
            "width": 120,
            "height": 90
          },
          "medium": {
            "url": "https://i.ytimg.com/vi/V0lw3qylVfY/mqdefault.jpg",
            "width": 320,
            "height": 180
          },
          "high": {
            "url": "https://i.ytimg.com/vi/V0lw3qylVfY/hqdefault.jpg",
            "width": 480,
            "height": 360
          }
        },
        "channelTitle": "XAmbassadorsVEVO",
        "liveBroadcastContent": "none",
        "publishTime": "2015-10-02T14:30:00Z"
      }
    },
    {
      "kind": "youtube#searchResult",
      "etag": "qZt0PW6VXf8Rr45T0l8AQTkvD8M",
      "id": {
        "kind": "youtube#video",
        "videoId": "pFjryf8zH_M"
      },
      "snippet": {
        "publishedAt": "2015-07-03T10:40:23Z",
        "channelId": "UC-gl-4XCIcCj1qj-bA6xhCw",
        "title": "X Ambassadors - Unsteady (Lyrics)",
        "description": "The Dream You Need X Ambassadors - UNSTEADY | Official Dance Video #LoveisLove https://www.youtube.com/watch?v=GsVXnCGij5o&feature=youtu.be X ...",
        "thumbnails": {
          "default": {
            "url": "https://i.ytimg.com/vi/pFjryf8zH_M/default.jpg",
            "width": 120,
            "height": 90
          },
          "medium": {
            "url": "https://i.ytimg.com/vi/pFjryf8zH_M/mqdefault.jpg",
            "width": 320,
            "height": 180
          },
          "high": {
            "url": "https://i.ytimg.com/vi/pFjryf8zH_M/hqdefault.jpg",
            "width": 480,
            "height": 360
          }
        },
        "channelTitle": "EliotSDX",
        "liveBroadcastContent": "none",
        "publishTime": "2015-07-03T10:40:23Z"
      }
    },
    {
      "kind": "youtube#searchResult",
      "etag": "cOsjo3Mm9fJz6EzPPz_DcIcDhyw",
      "id": {
        "kind": "youtube#video",
        "videoId": "FGdaSDwKPG8"
      },
      "snippet": {
        "publishedAt": "2016-04-22T04:00:24Z",
        "channelId": "UCjmJDM5pRKbUlVIzDYYWb6g",
        "title": "Me Before You - X Ambassadors &quot;Unsteady&quot; (Erich Lee Gravity Remix)",
        "description": "On June 3rd #LiveBoldly http://MeBeforeYouMovie.com https://www.facebook.com/MeBeforeYouMovie/ Soundtrack: http://smarturl.it/MeBeforeYou Based on the ...",
        "thumbnails": {
          "default": {
            "url": "https://i.ytimg.com/vi/FGdaSDwKPG8/default.jpg",
            "width": 120,
            "height": 90
          },
          "medium": {
            "url": "https://i.ytimg.com/vi/FGdaSDwKPG8/mqdefault.jpg",
            "width": 320,
            "height": 180
          },
          "high": {
            "url": "https://i.ytimg.com/vi/FGdaSDwKPG8/hqdefault.jpg",
            "width": 480,
            "height": 360
          }
        },
        "channelTitle": "Warner Bros. Pictures",
        "liveBroadcastContent": "none",
        "publishTime": "2016-04-22T04:00:24Z"
      }
    }
  ]
}
